aiapy/CITATION.rst
aiapy/__init__.py
aiapy/_version.py
aiapy/conftest.py
aiapy/version.py
aiapy/calibrate/__init__.py
aiapy/calibrate/meta.py
aiapy/calibrate/prep.py
aiapy/calibrate/spikes.py
aiapy/calibrate/transform.py
aiapy/calibrate/uncertainty.py
aiapy/calibrate/utils.py
aiapy/calibrate/tests/__init__.py
aiapy/calibrate/tests/test_meta.py
aiapy/calibrate/tests/test_prep.py
aiapy/calibrate/tests/test_spikes.py
aiapy/calibrate/tests/test_uncertainty.py
aiapy/calibrate/tests/test_utils.py
aiapy/data/README.rst
aiapy/data/__init__.py
aiapy/data/_manager.py
aiapy/data/_sample.py
aiapy/data/sample.py
aiapy/psf/__init__.py
aiapy/psf/deconvolve.py
aiapy/psf/psf.py
aiapy/psf/utils.py
aiapy/psf/tests/__init__.py
aiapy/psf/tests/conftest.py
aiapy/psf/tests/test_deconvolve.py
aiapy/psf/tests/test_psf.py
aiapy/psf/tests/test_utils.py
aiapy/response/__init__.py
aiapy/response/channel.py
aiapy/response/tests/__init__.py
aiapy/response/tests/test_channel.py
aiapy/tests/__init__.py
aiapy/tests/test_idl.py
aiapy/tests/test_init.py
aiapy/tests/data/__init__.py
aiapy/tests/data/aia_V3_error_table.txt
aiapy/tests/data/aia_V8_20171210_050627_response_table.txt
aiapy/utils/__init__.py
aiapy/utils/decorators.py
aiapy/utils/exceptions.py
aiapy/utils/net.py
aiapy/utils/utils.py
aiapy/utils/tests/__init__.py
aiapy/utils/tests/test_net.py
aiapy/utils/tests/test_utils.py
aiapy-0.11.0.dist-info/licenses/LICENSE.rst
aiapy-0.11.0.dist-info/METADATA
aiapy-0.11.0.dist-info/WHEEL
aiapy-0.11.0.dist-info/top_level.txt
aiapy-0.11.0.dist-info/RECORD
