Metadata-Version: 2.4
Name: aiapy
Version: 0.11.0
Summary: Python library for AIA data analysis.
Author-email: "AIA Instrument Team @ LMSAL" <nfreij@set.org>
Project-URL: Homepage, https://aia.lmsal.com/
Project-URL: Source Code, https://github.com/LM-SAL/aiapy
Project-URL: Download, https://pypi.org/project/aiapy
Project-URL: Documentation, https://aiapy.readthedocs.io/en/stable/
Project-URL: Changelog, https://aiapy.readthedocs.io/en/stable/changelog.html
Project-URL: Issue Tracker, https://github.com/LM-SAL/aiapy/issues/
Keywords: solar physics,solar,science,NASA,SDO,AIA,solar dynamics observatory,atmospheric imaging assembly
Classifier: Development Status :: 4 - Beta
Classifier: Intended Audience :: Science/Research
Classifier: License :: OSI Approved :: BSD License
Classifier: Natural Language :: English
Classifier: Operating System :: OS Independent
Classifier: Programming Language :: Python
Classifier: Programming Language :: Python :: 3
Classifier: Programming Language :: Python :: 3.11
Classifier: Programming Language :: Python :: 3.12
Classifier: Programming Language :: Python :: 3.13
Classifier: Programming Language :: Python :: 3.14
Classifier: Topic :: Scientific/Engineering :: Astronomy
Requires-Python: >=3.12
License-File: LICENSE.rst
Requires-Dist: sunpy[image,map,net]>=7.0
Provides-Extra: all
Requires-Dist: aiapy; extra == "all"
Provides-Extra: performance
Requires-Dist: jax; extra == "performance"
Provides-Extra: performance-nvidia
Requires-Dist: jax[cuda13]; extra == "performance-nvidia"
Provides-Extra: performance-mac
Requires-Dist: jax-metal; sys_platform == "darwin" and extra == "performance-mac"
Provides-Extra: tests
Requires-Dist: pytest; extra == "tests"
Requires-Dist: pytest-doctestplus; extra == "tests"
Requires-Dist: pytest-cov; extra == "tests"
Requires-Dist: pytest-xdist; extra == "tests"
Requires-Dist: aiapy[all]; extra == "tests"
Requires-Dist: hissw; extra == "tests"
Requires-Dist: pytest-astropy; extra == "tests"
Provides-Extra: docs
Requires-Dist: sphinx; extra == "docs"
Requires-Dist: sphinx-automodapi; extra == "docs"
Requires-Dist: sphinx-changelog; extra == "docs"
Requires-Dist: packaging; extra == "docs"
Requires-Dist: aiapy[all]; extra == "docs"
Requires-Dist: sphinx-copybutton; extra == "docs"
Requires-Dist: sphinx-design; extra == "docs"
Requires-Dist: sphinx-gallery; extra == "docs"
Requires-Dist: sphinxext-opengraph; extra == "docs"
Requires-Dist: sunpy-sphinx-theme; extra == "docs"
Requires-Dist: sunpy-sphinx-theme; extra == "docs"
Provides-Extra: dev
Requires-Dist: aiapy[all,docs,tests]; extra == "dev"
Dynamic: license-file
